Workbook

Sheet メニュー原価一覧
A1: RAKU SPA 1010 神田 メニュー別 原価・粗利益一覧
A2: メニュー構成：メニューリスト「250508更新」準拠（価格はメニュー表2506 PDF）／原価：2024 GMレシピ
C3: 改訂前 | D3: 改訂後
A4: 消費税率 | C4: 0.1 | D4: 0.1 | F4: 値上げ品数 | G4: =COUNTIF(N11:N159,">0") -> 125
A5: メニュー数 | C5: =COUNTA(D11:D159) -> 149 | D5: =COUNTA(D11:D159) -> 149 | F5: 平均値上げ幅（税込） | G5: =IFERROR(AVERAGEIF(N11:N159,">0"),"") -> 29.52
A6: 平均原価率 | C6: =IFERROR(AVERAGEIF(G11:G159,">0",H11:H159),"") -> 0.28549818 | D6: =IFERROR(AVERAGEIF(G11:G159,">0",L11:L159),"") -> 0.27575208 | F6: 平均値上げ率 | G6: =IFERROR(SUMPRODUCT((N11:N159>0)*(J11:J159/E11:E159-1))/G4,"") -> 0.040837914
A7: 平均粗利益 | C7: =IFERROR(AVERAGEIF(G11:G159,">0",I11:I159),"") -> 516.42248 | D7: =IFERROR(AVERAGEIF(G11:G159,">0",M11:M159),"") -> 539.07316
A8: 原価未登録 | C8: =COUNTA(D11:D159)-COUNTIF(G11:G159,">0") -> 3
J9: 値上げ→
A10: No. | B10: 区分 | C10: 分類 | D10: メニュー名 | E10: 税込価格 | F10: 税抜価格 | G10: 原価（税抜）✎入力 | H10: 原価率 | I10: 粗利益 | J10: 税込価格✎入力 | K10: 税抜価格 | L10: 原価率 | M10: 粗利益 | N10: 価格差（税込） | O10: 備考
A11: 1 | B11: ドリンク | C11: ビール | D11: アサヒスーパードライ（パイントグラス） | E11: 855 | F11: =IF(E11="","",ROUND(E11/(1+$C$4),0)) -> 777 | G11: 284.4 | H11: =IF(OR(F11="",F11=0,G11=""),"",G11/F11) -> 0.36602317 | I11: =IF(OR(F11="",G11=""),"",F11-G11) -> 492.6 | J11: 855 | K11: =IF(J11="","",ROUND(J11/(1+$D$4),0)) -> 777 | L11: =IF(OR(K11="",K11=0,G11=""),"",G11/K11) -> 0.36602317 | M11: =IF(OR(K11="",G11=""),"",K11-G11) -> 492.6 | N11: =J11-E11 -> 0
A12: 2 | B12: ドリンク | C12: ビール | D12: マルエフ | E12: 855 | F12: =IF(E12="","",ROUND(E12/(1+$C$4),0)) -> 777 | G12: 307.2 | H12: =IF(OR(F12="",F12=0,G12=""),"",G12/F12) -> 0.3953668 | I12: =IF(OR(F12="",G12=""),"",F12-G12) -> 469.8 | J12: 855 | K12: =IF(J12="","",ROUND(J12/(1+$D$4),0)) -> 777 | L12: =IF(OR(K12="",K12=0,G12=""),"",G12/K12) -> 0.3953668 | M12: =IF(OR(K12="",G12=""),"",K12-G12) -> 469.8 | N12: =J12-E12 -> 0 | O12: レシピなし／原価未登録
A13: 3 | B13: ドリンク | C13: ビール | D13: 熟撰 | E13: 855 | F13: =IF(E13="","",ROUND(E13/(1+$C$4),0)) -> 777 | G13: 321.7 | H13: =IF(OR(F13="",F13=0,G13=""),"",G13/F13) -> 0.41402831 | I13: =IF(OR(F13="",G13=""),"",F13-G13) -> 455.3 | J13: 855 | K13: =IF(J13="","",ROUND(J13/(1+$D$4),0)) -> 777 | L13: =IF(OR(K13="",K13=0,G13=""),"",G13/K13) -> 0.41402831 | M13: =IF(OR(K13="",G13=""),"",K13-G13) -> 455.3 | N13: =J13-E13 -> 0 | O13: レシピなし／原価未登録
A14: 4 | B14: ドリンク | C14: ビール | D14: 黒生 | E14: 855 | F14: =IF(E14="","",ROUND(E14/(1+$C$4),0)) -> 777 | G14: 307.2 | H14: =IF(OR(F14="",F14=0,G14=""),"",G14/F14) -> 0.3953668 | I14: =IF(OR(F14="",G14=""),"",F14-G14) -> 469.8 | J14: 855 | K14: =IF(J14="","",ROUND(J14/(1+$D$4),0)) -> 777 | L14: =IF(OR(K14="",K14=0,G14=""),"",G14/K14) -> 0.3953668 | M14: =IF(OR(K14="",G14=""),"",K14-G14) -> 469.8 | N14: =J14-E14 -> 0 | O14: レシピなし／原価未登録
A15: 5 | B15: ドリンク | C15: ビール | D15: 1010JUGビール（800ml） | E15: 1023 | F15: =IF(E15="","",ROUND(E15/(1+$C$4),0)) -> 930 | G15: 568.8 | H15: =IF(OR(F15="",F15=0,G15=""),"",G15/F15) -> 0.6116129 | I15: =IF(OR(F15="",G15=""),"",F15-G15) -> 361.2 | J15: 1353 | K15: =IF(J15="","",ROUND(J15/(1+$D$4),0)) -> 1230 | L15: =IF(OR(K15="",K15=0,G15=""),"",G15/K15) -> 0.46243902 | M15: =IF(OR(K15="",G15=""),"",K15-G15) -> 661.2 | N15: =J15-E15 -> 330 | O15: レシピなし／原価未登録
A16: 6 | B16: ドリンク | C16: ビール | D16: ペローニ | E16: 968 | F16: =IF(E16="","",ROUND(E16/(1+$C$4),0)) -> 880 | G16: 310 | H16: =IF(OR(F16="",F16=0,G16=""),"",G16/F16) -> 0.35227273 | I16: =IF(OR(F16="",G16=""),"",F16-G16) -> 570 | J16: 988 | K16: =IF(J16="","",ROUND(J16/(1+$D$4),0)) -> 898 | L16: =IF(OR(K16="",K16=0,G16=""),"",G16/K16) -> 0.34521158 | M16: =IF(OR(K16="",G16=""),"",K16-G16) -> 588 | N16: =J16-E16 -> 20
A17: 7 | B17: ドリンク | C17: ビール | D17: カールスバーグ | E17: 968 | F17: =IF(E17="","",ROUND(E17/(1+$C$4),0)) -> 880 | G17: 215 | H17: =IF(OR(F17="",F17=0,G17=""),"",G17/F17) -> 0.24431818 | I17: =IF(OR(F17="",G17=""),"",F17-G17) -> 665 | J17: 988 | K17: =IF(J17="","",ROUND(J17/(1+$D$4),0)) -> 898 | L17: =IF(OR(K17="",K17=0,G17=""),"",G17/K17) -> 0.23942094 | M17: =IF(OR(K17="",G17=""),"",K17-G17) -> 683 | N17: =J17-E17 -> 20
A18: 8 | B18: ドリンク | C18: ビール | D18: ピルスナー・ウルケル | E18: 968 | F18: =IF(E18="","",ROUND(E18/(1+$C$4),0)) -> 880 | G18: 296 | H18: =IF(OR(F18="",F18=0,G18=""),"",G18/F18) -> 0.33636364 | I18: =IF(OR(F18="",G18=""),"",F18-G18) -> 584 | J18: 988 | K18: =IF(J18="","",ROUND(J18/(1+$D$4),0)) -> 898 | L18: =IF(OR(K18="",K18=0,G18=""),"",G18/K18) -> 0.32962138 | M18: =IF(OR(K18="",G18=""),"",K18-G18) -> 602 | N18: =J18-E18 -> 20
A19: 9 | B19: ドリンク | C19: ビール | D19: アサヒドライゼロ（ノンアル） | E19: 583 | F19: =IF(E19="","",ROUND(E19/(1+$C$4),0)) -> 530 | G19: 169.7 | H19: =IF(OR(F19="",F19=0,G19=""),"",G19/F19) -> 0.32018868 | I19: =IF(OR(F19="",G19=""),"",F19-G19) -> 360.3 | J19: 638 | K19: =IF(J19="","",ROUND(J19/(1+$D$4),0)) -> 580 | L19: =IF(OR(K19="",K19=0,G19=""),"",G19/K19) -> 0.29258621 | M19: =IF(OR(K19="",G19=""),"",K19-G19) -> 410.3 | N19: =J19-E19 -> 55 | O19: レシピなし／原価未登録
A20: 10 | B20: ドリンク | C20: ハイボール | D20: ハイボール | E20: 748 | F20: =IF(E20="","",ROUND(E20/(1+$C$4),0)) -> 680 | G20: 53.5 | H20: =IF(OR(F20="",F20=0,G20=""),"",G20/F20) -> 0.078676471 | I20: =IF(OR(F20="",G20=""),"",F20-G20) -> 626.5 | J20: 748 | K20: =IF(J20="","",ROUND(J20/(1+$D$4),0)) -> 680 | L20: =IF(OR(K20="",K20=0,G20=""),"",G20/K20) -> 0.078676471 | M20: =IF(OR(K20="",G20=""),"",K20-G20) -> 626.5 | N20: =J20-E20 -> 0 | O20: レギュラー748／大容量1,023。レシピ名「1010JUGハイボール」
A21: 11 | B21: ドリンク | C21: ハイボール | D21: コークハイ | E21: 748 | F21: =IF(E21="","",ROUND(E21/(1+$C$4),0)) -> 680 | G21: 172 | H21: =IF(OR(F21="",F21=0,G21=""),"",G21/F21) -> 0.25294118 | I21: =IF(OR(F21="",G21=""),"",F21-G21) -> 508 | J21: 748 | K21: =IF(J21="","",ROUND(J21/(1+$D$4),0)) -> 680 | L21: =IF(OR(K21="",K21=0,G21=""),"",G21/K21) -> 0.25294118 | M21: =IF(OR(K21="",G21=""),"",K21-G21) -> 508 | N21: =J21-E21 -> 0 | O21: レギュラー748／大容量1,023
A22: 12 | B22: ドリンク | C22: ハイボール | D22: ジンジャーハイ | E22: 748 | F22: =IF(E22="","",ROUND(E22/(1+$C$4),0)) -> 680 | G22: 226.2 | H22: =IF(OR(F22="",F22=0,G22=""),"",G22/F22) -> 0.33264706 | I22: =IF(OR(F22="",G22=""),"",F22-G22) -> 453.8 | J22: 748 | K22: =IF(J22="","",ROUND(J22/(1+$D$4),0)) -> 680 | L22: =IF(OR(K22="",K22=0,G22=""),"",G22/K22) -> 0.33264706 | M22: =IF(OR(K22="",G22=""),"",K22-G22) -> 453.8 | N22: =J22-E22 -> 0 | O22: レギュラー748／大容量1,023
A23: 13 | B23: ドリンク | C23: ハイボール | D23: むぎハイ | E23: 748 | F23: =IF(E23="","",ROUND(E23/(1+$C$4),0)) -> 680 | G23: 149.1 | H23: =IF(OR(F23="",F23=0,G23=""),"",G23/F23) -> 0.21926471 | I23: =IF(OR(F23="",G23=""),"",F23-G23) -> 530.9 | J23: 748 | K23: =IF(J23="","",ROUND(J23/(1+$D$4),0)) -> 680 | L23: =IF(OR(K23="",K23=0,G23=""),"",G23/K23) -> 0.21926471 | M23: =IF(OR(K23="",G23=""),"",K23-G23) -> 530.9 | N23: =J23-E23 -> 0 | O23: レギュラー748／大容量1,023
A24: 14 | B24: ドリンク | C24: ハイボール | D24: いもハイ | E24: 748 | F24: =IF(E24="","",ROUND(E24/(1+$C$4),0)) -> 680 | G24: 124.1 | H24: =IF(OR(F24="",F24=0,G24=""),"",G24/F24) -> 0.1825 | I24: =IF(OR(F24="",G24=""),"",F24-G24) -> 555.9 | J24: 748 | K24: =IF(J24="","",ROUND(J24/(1+$D$4),0)) -> 680 | L24: =IF(OR(K24="",K24=0,G24=""),"",G24/K24) -> 0.1825 | M24: =IF(OR(K24="",G24=""),"",K24-G24) -> 555.9 | N24: =J24-E24 -> 0 | O24: レギュラー748／大容量1,023
A25: 15 | B25: ドリンク | C25: サワー | D25: マンゴーサワー | E25: 638 | F25: =IF(E25="","",ROUND(E25/(1+$C$4),0)) -> 580 | G25: 133.6 | H25: =IF(OR(F25="",F25=0,G25=""),"",G25/F25) -> 0.23034483 | I25: =IF(OR(F25="",G25=""),"",F25-G25) -> 446.4 | J25: 638 | K25: =IF(J25="","",ROUND(J25/(1+$D$4),0)) -> 580 | L25: =IF(OR(K25="",K25=0,G25=""),"",G25/K25) -> 0.23034483 | M25: =IF(OR(K25="",G25=""),"",K25-G25) -> 446.4 | N25: =J25-E25 -> 0
A26: 16 | B26: ドリンク | C26: サワー | D26: いちごサワー | E26: 638 | F26: =IF(E26="","",ROUND(E26/(1+$C$4),0)) -> 580 | G26: 121.1 | H26: =IF(OR(F26="",F26=0,G26=""),"",G26/F26) -> 0.2087931 | I26: =IF(OR(F26="",G26=""),"",F26-G26) -> 458.9 | J26: 638 | K26: =IF(J26="","",ROUND(J26/(1+$D$4),0)) -> 580 | L26: =IF(OR(K26="",K26=0,G26=""),"",G26/K26) -> 0.2087931 | M26: =IF(OR(K26="",G26=""),"",K26-G26) -> 458.9 | N26: =J26-E26 -> 0 | O26: レシピなし／原価未登録
A27: 17 | B27: ドリンク | C27: サワー | D27: カルピスサワー | E27: 638 | F27: =IF(E27="","",ROUND(E27/(1+$C$4),0)) -> 580 | G27: 89.3 | H27: =IF(OR(F27="",F27=0,G27=""),"",G27/F27) -> 0.15396552 | I27: =IF(OR(F27="",G27=""),"",F27-G27) -> 490.7 | J27: 638 | K27: =IF(J27="","",ROUND(J27/(1+$D$4),0)) -> 580 | L27: =IF(OR(K27="",K27=0,G27=""),"",G27/K27) -> 0.15396552 | M27: =IF(OR(K27="",G27=""),"",K27-G27) -> 490.7 | N27: =J27-E27 -> 0
A28: 18 | B28: ドリンク | C28: サワー | D28: ウーロンハイ | E28: 638 | F28: =IF(E28="","",ROUND(E28/(1+$C$4),0)) -> 580 | G28: 55.3 | H28: =IF(OR(F28="",F28=0,G28=""),"",G28/F28) -> 0.095344828 | I28: =IF(OR(F28="",G28=""),"",F28-G28) -> 524.7 | J28: 638 | K28: =IF(J28="","",ROUND(J28/(1+$D$4),0)) -> 580 | L28: =IF(OR(K28="",K28=0,G28=""),"",G28/K28) -> 0.095344828 | M28: =IF(OR(K28="",G28=""),"",K28-G28) -> 524.7 | N28: =J28-E28 -> 0 | O28: レシピなし／原価未登録
A29: 19 | B29: ドリンク | C29: サワー | D29: 匠の深絞りレモンサワー | E29: 638 | F29: =IF(E29="","",ROUND(E29/(1+$C$4),0)) -> 580 | G29: 76.42885 | H29: =IF(OR(F29="",F29=0,G29=""),"",G29/F29) -> 0.13177388 | I29: =IF(OR(F29="",G29=""),"",F29-G29) -> 503.57115 | J29: 638 | K29: =IF(J29="","",ROUND(J29/(1+$D$4),0)) -> 580 | L29: =IF(OR(K29="",K29=0,G29=""),"",G29/K29) -> 0.13177388 | M29: =IF(OR(K29="",G29=""),"",K29-G29) -> 503.57115 | N29: =J29-E29 -> 0
A30: 20 | B30: ドリンク | C30: サワー | D30: シチリアレモンサワー | E30: 638 | F30: =IF(E30="","",ROUND(E30/(1+$C$4),0)) -> 580 | G30: 80.4 | H30: =IF(OR(F30="",F30=0,G30=""),"",G30/F30) -> 0.13862069 | I30: =IF(OR(F30="",G30=""),"",F30-G30) -> 499.6 | J30: 638 | K30: =IF(J30="","",ROUND(J30/(1+$D$4),0)) -> 580 | L30: =IF(OR(K30="",K30=0,G30=""),"",G30/K30) -> 0.13862069 | M30: =IF(OR(K30="",G30=""),"",K30-G30) -> 499.6 | N30: =J30-E30 -> 0
A31: 21 | B31: ドリンク | C31: サワー | D31: 塩ライチサワー | E31: 638 | F31: =IF(E31="","",ROUND(E31/(1+$C$4),0)) -> 580 | G31: 81.8 | H31: =IF(OR(F31="",F31=0,G31=""),"",G31/F31) -> 0.14103448 | I31: =IF(OR(F31="",G31=""),"",F31-G31) -> 498.2 | J31: 638 | K31: =IF(J31="","",ROUND(J31/(1+$D$4),0)) -> 580 | L31: =IF(OR(K31="",K31=0,G31=""),"",G31/K31) -> 0.14103448 | M31: =IF(OR(K31="",G31=""),"",K31-G31) -> 498.2 | N31: =J31-E31 -> 0 | O31: レシピなし／原価未登録
A32: 22 | B32: ドリンク | C32: サワー | D32: 塩レモンサワー | E32: 638 | F32: =IF(E32="","",ROUND(E32/(1+$C$4),0)) -> 580 | G32: 81.8 | H32: =IF(OR(F32="",F32=0,G32=""),"",G32/F32) -> 0.14103448 | I32: =IF(OR(F32="",G32=""),"",F32-G32) -> 498.2 | J32: 638 | K32: =IF(J32="","",ROUND(J32/(1+$D$4),0)) -> 580 | L32: =IF(OR(K32="",K32=0,G32=""),"",G32/K32) -> 0.14103448 | M32: =IF(OR(K32="",G32=""),"",K32-G32) -> 498.2 | N32: =J32-E32 -> 0 | O32: レシピなし／原価未登録
A33: 23 | B33: ドリンク | C33: サワー | D33: 塩オレンジサワー | E33: 638 | F33: =IF(E33="","",ROUND(E33/(1+$C$4),0)) -> 580 | G33: 80.4 | H33: =IF(OR(F33="",F33=0,G33=""),"",G33/F33) -> 0.13862069 | I33: =IF(OR(F33="",G33=""),"",F33-G33) -> 499.6 | J33: 638 | K33: =IF(J33="","",ROUND(J33/(1+$D$4),0)) -> 580 | L33: =IF(OR(K33="",K33=0,G33=""),"",G33/K33) -> 0.13862069 | M33: =IF(OR(K33="",G33=""),"",K33-G33) -> 499.6 | N33: =J33-E33 -> 0 | O33: レシピなし／原価未登録
A34: 24 | B34: ドリンク | C34: カクテル・蒸留酒・焼酎 | D34: カシスオレンジ | E34: 638 | F34: =IF(E34="","",ROUND(E34/(1+$C$4),0)) -> 580 | G34: 243.6 | H34: =IF(OR(F34="",F34=0,G34=""),"",G34/F34) -> 0.42 | I34: =IF(OR(F34="",G34=""),"",F34-G34) -> 336.4 | J34: 638 | K34: =IF(J34="","",ROUND(J34/(1+$D$4),0)) -> 580 | L34: =IF(OR(K34="",K34=0,G34=""),"",G34/K34) -> 0.42 | M34: =IF(OR(K34="",G34=""),"",K34-G34) -> 336.4 | N34: =J34-E34 -> 0
A35: 25 | B35: ドリンク | C35: カクテル・蒸留酒・焼酎 | D35: カシスソーダ | E35: 638 | F35: =IF(E35="","",ROUND(E35/(1+$C$4),0)) -> 580 | G35: 91 | H35: =IF(OR(F35="",F35=0,G35=""),"",G35/F35) -> 0.15689655 | I35: =IF(OR(F35="",G35=""),"",F35-G35) -> 489 | J35: 658 | K35: =IF(J35="","",ROUND(J35/(1+$D$4),0)) -> 598 | L35: =IF(OR(K35="",K35=0,G35=""),"",G35/K35) -> 0.15217391 | M35: =IF(OR(K35="",G35=""),"",K35-G35) -> 507 | N35: =J35-E35 -> 20
A36: 26 | B36: ドリンク | C36: カクテル・蒸留酒・焼酎 | D36: フォション大人のミルクティー | E36: 638 | F36: =IF(E36="","",ROUND(E36/(1+$C$4),0)) -> 580 | G36: 139.1 | H36: =IF(OR(F36="",F36=0,G36=""),"",G36/F36) -> 0.23982759 | I36: =IF(OR(F36="",G36=""),"",F36-G36) -> 440.9 | J36: 658 | K36: =IF(J36="","",ROUND(J36/(1+$D$4),0)) -> 598 | L36: =IF(OR(K36="",K36=0,G36=""),"",G36/K36) -> 0.2326087 | M36: =IF(OR(K36="",G36=""),"",K36-G36) -> 458.9 | N36: =J36-E36 -> 20
A37: 27 | B37: ドリンク | C37: カクテル・蒸留酒・焼酎 | D37: モスコミュール | E37: 638 | F37: =IF(E37="","",ROUND(E37/(1+$C$4),0)) -> 580 | G37: 116.2 | H37: =IF(OR(F37="",F37=0,G37=""),"",G37/F37) -> 0.20034483 | I37: =IF(OR(F37="",G37=""),"",F37-G37) -> 463.8 | J37: 658 | K37: =IF(J37="","",ROUND(J37/(1+$D$4),0)) -> 598 | L37: =IF(OR(K37="",K37=0,G37=""),"",G37/K37) -> 0.19431438 | M37: =IF(OR(K37="",G37=""),"",K37-G37) -> 481.8 | N37: =J37-E37 -> 20
A38: 28 | B38: ドリンク | C38: カクテル・蒸留酒・焼酎 | D38: ウィルキンソン ジン（ソーダ割） | E38: 638 | F38: =IF(E38="","",ROUND(E38/(1+$C$4),0)) -> 580 | G38: 49.579643 | H38: =IF(OR(F38="",F38=0,G38=""),"",G38/F38) -> 0.085482144 | I38: =IF(OR(F38="",G38=""),"",F38-G38) -> 530.42036 | J38: 658 | K38: =IF(J38="","",ROUND(J38/(1+$D$4),0)) -> 598 | L38: =IF(OR(K38="",K38=0,G38=""),"",G38/K38) -> 0.082909103 | M38: =IF(OR(K38="",G38=""),"",K38-G38) -> 548.42036 | N38: =J38-E38 -> 20
A39: 29 | B39: ドリンク | C39: カクテル・蒸留酒・焼酎 | D39: ウィルキンソン ウォッカ（ソーダ割） | E39: 638 | F39: =IF(E39="","",ROUND(E39/(1+$C$4),0)) -> 580 | G39: 49.579643 | H39: =IF(OR(F39="",F39=0,G39=""),"",G39/F39) -> 0.085482144 | I39: =IF(OR(F39="",G39=""),"",F39-G39) -> 530.42036 | J39: 658 | K39: =IF(J39="","",ROUND(J39/(1+$D$4),0)) -> 598 | L39: =IF(OR(K39="",K39=0,G39=""),"",G39/K39) -> 0.082909103 | M39: =IF(OR(K39="",G39=""),"",K39-G39) -> 548.42036 | N39: =J39-E39 -> 20
A40: 30 | B40: ドリンク | C40: カクテル・蒸留酒・焼酎 | D40: 麦焼酎 | E40: 638 | F40: =IF(E40="","",ROUND(E40/(1+$C$4),0)) -> 580 | G40: 78.8 | H40: =IF(OR(F40="",F40=0,G40=""),"",G40/F40) -> 0.13586207 | I40: =IF(OR(F40="",G40=""),"",F40-G40) -> 501.2 | J40: 658 | K40: =IF(J40="","",ROUND(J40/(1+$D$4),0)) -> 598 | L40: =IF(OR(K40="",K40=0,G40=""),"",G40/K40) -> 0.13177258 | M40: =IF(OR(K40="",G40=""),"",K40-G40) -> 519.2 | N40: =J40-E40 -> 20 | O40: ソーダ割・水割り・ロック
A41: 31 | B41: ドリンク | C41: カクテル・蒸留酒・焼酎 | D41: 芋焼酎 | E41: 638 | F41: =IF(E41="","",ROUND(E41/(1+$C$4),0)) -> 580 | G41: 66.4 | H41: =IF(OR(F41="",F41=0,G41=""),"",G41/F41) -> 0.11448276 | I41: =IF(OR(F41="",G41=""),"",F41-G41) -> 513.6 | J41: 658 | K41: =IF(J41="","",ROUND(J41/(1+$D$4),0)) -> 598 | L41: =IF(OR(K41="",K41=0,G41=""),"",G41/K41) -> 0.11103679 | M41: =IF(OR(K41="",G41=""),"",K41-G41) -> 531.6 | N41: =J41-E41 -> 20 | O41: ソーダ割・水割り・ロック
A42: 32 | B42: ドリンク | C42: ワイン・果実酒 | D42: ガリゲット・バリグール 赤（グラス180ml） | E42: 583 | F42: =IF(E42="","",ROUND(E42/(1+$C$4),0)) -> 530 | G42: 166.6 | H42: =IF(OR(F42="",F42=0,G42=""),"",G42/F42) -> 0.31433962 | I42: =IF(OR(F42="",G42=""),"",F42-G42) -> 363.4 | J42: 613 | K42: =IF(J42="","",ROUND(J42/(1+$D$4),0)) -> 557 | L42: =IF(OR(K42="",K42=0,G42=""),"",G42/K42) -> 0.29910233 | M42: =IF(OR(K42="",G42=""),"",K42-G42) -> 390.4 | N42: =J42-E42 -> 30 | O42: レシピなし／原価未登録
A43: 33 | B43: ドリンク | C43: ワイン・果実酒 | D43: ガリゲット・バリグール 赤（ボトル750ml） | E43: 1958 | F43: =IF(E43="","",ROUND(E43/(1+$C$4),0)) -> 1780 | G43: 680 | H43: =IF(OR(F43="",F43=0,G43=""),"",G43/F43) -> 0.38202247 | I43: =IF(OR(F43="",G43=""),"",F43-G43) -> 1100 | J43: 1978 | K43: =IF(J43="","",ROUND(J43/(1+$D$4),0)) -> 1798 | L43: =IF(OR(K43="",K43=0,G43=""),"",G43/K43) -> 0.378198 | M43: =IF(OR(K43="",G43=""),"",K43-G43) -> 1118 | N43: =J43-E43 -> 20 | O43: レシピなし／原価未登録
A44: 34 | B44: ドリンク | C44: ワイン・果実酒 | D44: ガリゲット・バリグール 白（グラス180ml） | E44: 583 | F44: =IF(E44="","",ROUND(E44/(1+$C$4),0)) -> 530 | G44: 166.6 | H44: =IF(OR(F44="",F44=0,G44=""),"",G44/F44) -> 0.31433962 | I44: =IF(OR(F44="",G44=""),"",F44-G44) -> 363.4 | J44: 613 | K44: =IF(J44="","",ROUND(J44/(1+$D$4),0)) -> 557 | L44: =IF(OR(K44="",K44=0,G44=""),"",G44/K44) -> 0.29910233 | M44: =IF(OR(K44="",G44=""),"",K44-G44) -> 390.4 | N44: =J44-E44 -> 30 | O44: レシピなし／原価未登録
A45: 35 | B45: ドリンク | C45: ワイン・果実酒 | D45: ガリゲット・バリグール 白（ボトル750ml） | E45: 1958 | F45: =IF(E45="","",ROUND(E45/(1+$C$4),0)) -> 1780 | G45: 680 | H45: =IF(OR(F45="",F45=0,G45=""),"",G45/F45) -> 0.38202247 | I45: =IF(OR(F45="",G45=""),"",F45-G45) -> 1100 | J45: 1978 | K45: =IF(J45="","",ROUND(J45/(1+$D$4),0)) -> 1798 | L45: =IF(OR(K45="",K45=0,G45=""),"",G45/K45) -> 0.378198 | M45: =IF(OR(K45="",G45=""),"",K45-G45) -> 1118 | N45: =J45-E45 -> 20 | O45: レシピなし／原価未登録
A46: 36 | B46: ドリンク | C46: ワイン・果実酒 | D46: マテウス ロゼ（187ml） | E46: 1298 | F46: =IF(E46="","",ROUND(E46/(1+$C$4),0)) -> 1180 | G46: 420 | H46: =IF(OR(F46="",F46=0,G46=""),"",G46/F46) -> 0.3559322 | I46: =IF(OR(F46="",G46=""),"",F46-G46) -> 760 | J46: 1318 | K46: =IF(J46="","",ROUND(J46/(1+$D$4),0)) -> 1198 | L46: =IF(OR(K46="",K46=0,G46=""),"",G46/K46) -> 0.35058431 | M46: =IF(OR(K46="",G46=""),"",K46-G46) -> 778 | N46: =J46-E46 -> 20 | O46: レシピなし／原価未登録
A47: 37 | B47: ドリンク | C47: ワイン・果実酒 | D47: ニッカ 弘前 生シードル ロゼ（200ml） | E47: 748 | F47: =IF(E47="","",ROUND(E47/(1+$C$4),0)) -> 680 | G47: 270 | H47: =IF(OR(F47="",F47=0,G47=""),"",G47/F47) -> 0.39705882 | I47: =IF(OR(F47="",G47=""),"",F47-G47) -> 410 | J47: 768 | K47: =IF(J47="","",ROUND(J47/(1+$D$4),0)) -> 698 | L47: =IF(OR(K47="",K47=0,G47=""),"",G47/K47) -> 0.38681948 | M47: =IF(OR(K47="",G47=""),"",K47-G47) -> 428 | N47: =J47-E47 -> 20 | O47: レシピなし／原価未登録
A48: 38 | B48: ドリンク | C48: ワイン・果実酒 | D48: 芳醇梅酒 | E48: 583 | F48: =IF(E48="","",ROUND(E48/(1+$C$4),0)) -> 530 | G48: 64.3 | H48: =IF(OR(F48="",F48=0,G48=""),"",G48/F48) -> 0.12132075 | I48: =IF(OR(F48="",G48=""),"",F48-G48) -> 465.7 | J48: 613 | K48: =IF(J48="","",ROUND(J48/(1+$D$4),0)) -> 557 | L48: =IF(OR(K48="",K48=0,G48=""),"",G48/K48) -> 0.11543986 | M48: =IF(OR(K48="",G48=""),"",K48-G48) -> 492.7 | N48: =J48-E48 -> 30 | O48: レシピなし／原価未登録／ソーダ割・水割り・ロック
A49: 39 | B49: ドリンク | C49: セット | D49: 1010セット（タパス付） | E49: 1111 | F49: =IF(E49="","",ROUND(E49/(1+$C$4),0)) -> 1010 | H49: =IF(OR(F49="",F49=0,G49=""),"",G49/F49) | I49: =IF(OR(F49="",G49=""),"",F49-G49) | J49: 1111 | K49: =IF(J49="","",ROUND(J49/(1+$D$4),0)) -> 1010 | L49: =IF(OR(K49="",K49=0,G49=""),"",G49/K49) | M49: =IF(OR(K49="",G49=""),"",K49-G49) | N49: =J49-E49 -> 0 | O49: レシピなし／原価未登録
A50: 40 | B50: ドリンク | C50: セット | D50: タパスセット | E50: 308 | F50: =IF(E50="","",ROUND(E50/(1+$C$4),0)) -> 280 | H50: =IF(OR(F50="",F50=0,G50=""),"",G50/F50) | I50: =IF(OR(F50="",G50=""),"",F50-G50) | J50: 308 | K50: =IF(J50="","",ROUND(J50/(1+$D$4),0)) -> 280 | L50: =IF(OR(K50="",K50=0,G50=""),"",G50/K50) | M50: =IF(OR(K50="",G50=""),"",K50-G50) | N50: =J50-E50 -> 0 | O50: レシピなし／原価未登録／アルコール注文時の追加料金
A51: 41 | B51: フード | C51: 冷製おつまみ | D51: カナッペ | E51: 748 | F51: =IF(E51="","",ROUND(E51/(1+$C$4),0)) -> 680 | G51: 177.3 | H51: =IF(OR(F51="",F51=0,G51=""),"",G51/F51) -> 0.26073529 | I51: =IF(OR(F51="",G51=""),"",F51-G51) -> 502.7 | J51: 768 | K51: =IF(J51="","",ROUND(J51/(1+$D$4),0)) -> 698 | L51: =IF(OR(K51="",K51=0,G51=""),"",G51/K51) -> 0.25401146 | M51: =IF(OR(K51="",G51=""),"",K51-G51) -> 520.7 | N51: =J51-E51 -> 20
A52: 42 | B52: フード | C52: 冷製おつまみ | D52: シュリンプカクテル | E52: 858 | F52: =IF(E52="","",ROUND(E52/(1+$C$4),0)) -> 780 | G52: 192.2 | H52: =IF(OR(F52="",F52=0,G52=""),"",G52/F52) -> 0.24641026 | I52: =IF(OR(F52="",G52=""),"",F52-G52) -> 587.8 | J52: 878 | K52: =IF(J52="","",ROUND(J52/(1+$D$4),0)) -> 798 | L52: =IF(OR(K52="",K52=0,G52=""),"",G52/K52) -> 0.24085213 | M52: =IF(OR(K52="",G52=""),"",K52-G52) -> 605.8 | N52: =J52-E52 -> 20
A53: 43 | B53: フード | C53: 冷製おつまみ | D53: ローストビーフユッケ | E53: 858 | F53: =IF(E53="","",ROUND(E53/(1+$C$4),0)) -> 780 | G53: 344.2 | H53: =IF(OR(F53="",F53=0,G53=""),"",G53/F53) -> 0.44128205 | I53: =IF(OR(F53="",G53=""),"",F53-G53) -> 435.8 | J53: 878 | K53: =IF(J53="","",ROUND(J53/(1+$D$4),0)) -> 798 | L53: =IF(OR(K53="",K53=0,G53=""),"",G53/K53) -> 0.43132832 | M53: =IF(OR(K53="",G53=""),"",K53-G53) -> 453.8 | N53: =J53-E53 -> 20
A54: 44 | B54: フード | C54: 冷製おつまみ | D54: irodori自家製ピクルス | E54: 583 | F54: =IF(E54="","",ROUND(E54/(1+$C$4),0)) -> 530 | G54: 172.2 | H54: =IF(OR(F54="",F54=0,G54=""),"",G54/F54) -> 0.32490566 | I54: =IF(OR(F54="",G54=""),"",F54-G54) -> 357.8 | J54: 603 | K54: =IF(J54="","",ROUND(J54/(1+$D$4),0)) -> 548 | L54: =IF(OR(K54="",K54=0,G54=""),"",G54/K54) -> 0.31423358 | M54: =IF(OR(K54="",G54=""),"",K54-G54) -> 375.8 | N54: =J54-E54 -> 20 | O54: レシピなし／原価未登録
A55: 45 | B55: フード | C55: 冷製おつまみ | D55: 生ハム＆カマンベールチーズ | E55: 748 | F55: =IF(E55="","",ROUND(E55/(1+$C$4),0)) -> 680 | G55: 257.9 | H55: =IF(OR(F55="",F55=0,G55=""),"",G55/F55) -> 0.37926471 | I55: =IF(OR(F55="",G55=""),"",F55-G55) -> 422.1 | J55: 768 | K55: =IF(J55="","",ROUND(J55/(1+$D$4),0)) -> 698 | L55: =IF(OR(K55="",K55=0,G55=""),"",G55/K55) -> 0.36948424 | M55: =IF(OR(K55="",G55=""),"",K55-G55) -> 440.1 | N55: =J55-E55 -> 20 | O55: レシピなし／原価未登録
A56: 46 | B56: フード | C56: 冷製おつまみ | D56: 生ハム | E56: 418 | F56: =IF(E56="","",ROUND(E56/(1+$C$4),0)) -> 380 | G56: 111.6 | H56: =IF(OR(F56="",F56=0,G56=""),"",G56/F56) -> 0.29368421 | I56: =IF(OR(F56="",G56=""),"",F56-G56) -> 268.4 | J56: 438 | K56: =IF(J56="","",ROUND(J56/(1+$D$4),0)) -> 398 | L56: =IF(OR(K56="",K56=0,G56=""),"",G56/K56) -> 0.28040201 | M56: =IF(OR(K56="",G56=""),"",K56-G56) -> 286.4 | N56: =J56-E56 -> 20 | O56: レシピなし／原価未登録
A57: 47 | B57: フード | C57: 冷製おつまみ | D57: カマンベールチーズ | E57: 418 | F57: =IF(E57="","",ROUND(E57/(1+$C$4),0)) -> 380 | G57: 211 | H57: =IF(OR(F57="",F57=0,G57=""),"",G57/F57) -> 0.55526316 | I57: =IF(OR(F57="",G57=""),"",F57-G57) -> 169 | J57: 438 | K57: =IF(J57="","",ROUND(J57/(1+$D$4),0)) -> 398 | L57: =IF(OR(K57="",K57=0,G57=""),"",G57/K57) -> 0.53015075 | M57: =IF(OR(K57="",G57=""),"",K57-G57) -> 187 | N57: =J57-E57 -> 20 | O57: レシピなし／原価未登録
A58: 48 | B58: フード | C58: 冷製おつまみ | D58: 枝豆 | E58: 473 | F58: =IF(E58="","",ROUND(E58/(1+$C$4),0)) -> 430 | G58: 77.6 | H58: =IF(OR(F58="",F58=0,G58=""),"",G58/F58) -> 0.18046512 | I58: =IF(OR(F58="",G58=""),"",F58-G58) -> 352.4 | J58: 493 | K58: =IF(J58="","",ROUND(J58/(1+$D$4),0)) -> 448 | L58: =IF(OR(K58="",K58=0,G58=""),"",G58/K58) -> 0.17321429 | M58: =IF(OR(K58="",G58=""),"",K58-G58) -> 370.4 | N58: =J58-E58 -> 20 | O58: レシピなし／原価未登録
A59: 49 | B59: フード | C59: 冷製おつまみ | D59: ガーリック枝豆 | E59: 528 | F59: =IF(E59="","",ROUND(E59/(1+$C$4),0)) -> 480 | G59: 93.9 | H59: =IF(OR(F59="",F59=0,G59=""),"",G59/F59) -> 0.195625 | I59: =IF(OR(F59="",G59=""),"",F59-G59) -> 386.1 | J59: 548 | K59: =IF(J59="","",ROUND(J59/(1+$D$4),0)) -> 498 | L59: =IF(OR(K59="",K59=0,G59=""),"",G59/K59) -> 0.18855422 | M59: =IF(OR(K59="",G59=""),"",K59-G59) -> 404.1 | N59: =J59-E59 -> 20
A60: 50 | B60: フード | C60: 冷製おつまみ | D60: サーモンマリネ | E60: 638 | F60: =IF(E60="","",ROUND(E60/(1+$C$4),0)) -> 580 | G60: 214.4 | H60: =IF(OR(F60="",F60=0,G60=""),"",G60/F60) -> 0.36965517 | I60: =IF(OR(F60="",G60=""),"",F60-G60) -> 365.6 | J60: 658 | K60: =IF(J60="","",ROUND(J60/(1+$D$4),0)) -> 598 | L60: =IF(OR(K60="",K60=0,G60=""),"",G60/K60) -> 0.35852843 | M60: =IF(OR(K60="",G60=""),"",K60-G60) -> 383.6 | N60: =J60-E60 -> 20
A61: 51 | B61: フード | C61: 冷製おつまみ | D61: ガーリックシュリンプ | E61: 638 | F61: =IF(E61="","",ROUND(E61/(1+$C$4),0)) -> 580 | G61: 373.2 | H61: =IF(OR(F61="",F61=0,G61=""),"",G61/F61) -> 0.64344828 | I61: =IF(OR(F61="",G61=""),"",F61-G61) -> 206.8 | J61: 658 | K61: =IF(J61="","",ROUND(J61/(1+$D$4),0)) -> 598 | L61: =IF(OR(K61="",K61=0,G61=""),"",G61/K61) -> 0.62408027 | M61: =IF(OR(K61="",G61=""),"",K61-G61) -> 224.8 | N61: =J61-E61 -> 20
A62: 52 | B62: フード | C62: 冷製おつまみ | D62: ミックスナッツ | E62: 418 | F62: =IF(E62="","",ROUND(E62/(1+$C$4),0)) -> 380 | G62: 167.4 | H62: =IF(OR(F62="",F62=0,G62=""),"",G62/F62) -> 0.44052632 | I62: =IF(OR(F62="",G62=""),"",F62-G62) -> 212.6 | J62: 438 | K62: =IF(J62="","",ROUND(J62/(1+$D$4),0)) -> 398 | L62: =IF(OR(K62="",K62=0,G62=""),"",G62/K62) -> 0.42060302 | M62: =IF(OR(K62="",G62=""),"",K62-G62) -> 230.6 | N62: =J62-E62 -> 20
A63: 53 | B63: フード | C63: 冷製おつまみ | D63: タパス | E63: 418 | F63: =IF(E63="","",ROUND(E63/(1+$C$4),0)) -> 380 | H63: =IF(OR(F63="",F63=0,G63=""),"",G63/F63) | I63: =IF(OR(F63="",G63=""),"",F63-G63) | J63: 438 | K63: =IF(J63="","",ROUND(J63/(1+$D$4),0)) -> 398 | L63: =IF(OR(K63="",K63=0,G63=""),"",G63/K63) | M63: =IF(OR(K63="",G63=""),"",K63-G63) | N63: =J63-E63 -> 20 | O63: レシピなし／原価未登録
A64: 54 | B64: フード | C64: 温製おつまみ | D64: 揚げ物盛り合わせ（からあげ・ポテト・イカ） | E64: 1408 | F64: =IF(E64="","",ROUND(E64/(1+$C$4),0)) -> 1280 | G64: 448.8 | H64: =IF(OR(F64="",F64=0,G64=""),"",G64/F64) -> 0.350625 | I64: =IF(OR(F64="",G64=""),"",F64-G64) -> 831.2 | J64: 1458 | K64: =IF(J64="","",ROUND(J64/(1+$D$4),0)) -> 1325 | L64: =IF(OR(K64="",K64=0,G64=""),"",G64/K64) -> 0.33871698 | M64: =IF(OR(K64="",G64=""),"",K64-G64) -> 876.2 | N64: =J64-E64 -> 50 | O64: レシピなし／原価未登録
A65: 55 | B65: フード | C65: 温製おつまみ | D65: イカの唐揚げ カラマリフリット | E65: 528 | F65: =IF(E65="","",ROUND(E65/(1+$C$4),0)) -> 480 | G65: 165.2 | H65: =IF(OR(F65="",F65=0,G65=""),"",G65/F65) -> 0.34416667 | I65: =IF(OR(F65="",G65=""),"",F65-G65) -> 314.8 | J65: 548 | K65: =IF(J65="","",ROUND(J65/(1+$D$4),0)) -> 498 | L65: =IF(OR(K65="",K65=0,G65=""),"",G65/K65) -> 0.33172691 | M65: =IF(OR(K65="",G65=""),"",K65-G65) -> 332.8 | N65: =J65-E65 -> 20 | O65: レシピなし／原価未登録
A66: 56 | B66: フード | C66: 温製おつまみ | D66: ポテトフライ | E66: 528 | F66: =IF(E66="","",ROUND(E66/(1+$C$4),0)) -> 480 | G66: 75.8 | H66: =IF(OR(F66="",F66=0,G66=""),"",G66/F66) -> 0.15791667 | I66: =IF(OR(F66="",G66=""),"",F66-G66) -> 404.2 | J66: 548 | K66: =IF(J66="","",ROUND(J66/(1+$D$4),0)) -> 498 | L66: =IF(OR(K66="",K66=0,G66=""),"",G66/K66) -> 0.15220884 | M66: =IF(OR(K66="",G66=""),"",K66-G66) -> 422.2 | N66: =J66-E66 -> 20 | O66: レシピなし／原価未登録
A67: 57 | B67: フード | C67: 温製おつまみ | D67: 特製からあげ | E67: 638 | F67: =IF(E67="","",ROUND(E67/(1+$C$4),0)) -> 580 | G67: 208.3 | H67: =IF(OR(F67="",F67=0,G67=""),"",G67/F67) -> 0.35913793 | I67: =IF(OR(F67="",G67=""),"",F67-G67) -> 371.7 | J67: 658 | K67: =IF(J67="","",ROUND(J67/(1+$D$4),0)) -> 598 | L67: =IF(OR(K67="",K67=0,G67=""),"",G67/K67) -> 0.34832776 | M67: =IF(OR(K67="",G67=""),"",K67-G67) -> 389.7 | N67: =J67-E67 -> 20
A68: 58 | B68: フード | C68: 温製おつまみ | D68: ピザポテト | E68: 583 | F68: =IF(E68="","",ROUND(E68/(1+$C$4),0)) -> 530 | G68: 167 | H68: =IF(OR(F68="",F68=0,G68=""),"",G68/F68) -> 0.31509434 | I68: =IF(OR(F68="",G68=""),"",F68-G68) -> 363 | J68: 603 | K68: =IF(J68="","",ROUND(J68/(1+$D$4),0)) -> 548 | L68: =IF(OR(K68="",K68=0,G68=""),"",G68/K68) -> 0.30474453 | M68: =IF(OR(K68="",G68=""),"",K68-G68) -> 381 | N68: =J68-E68 -> 20
A69: 59 | B69: フード | C69: 温製おつまみ | D69: カリカリチーズフライ | E69: 638 | F69: =IF(E69="","",ROUND(E69/(1+$C$4),0)) -> 580 | G69: 173 | H69: =IF(OR(F69="",F69=0,G69=""),"",G69/F69) -> 0.29827586 | I69: =IF(OR(F69="",G69=""),"",F69-G69) -> 407 | J69: 658 | K69: =IF(J69="","",ROUND(J69/(1+$D$4),0)) -> 598 | L69: =IF(OR(K69="",K69=0,G69=""),"",G69/K69) -> 0.28929766 | M69: =IF(OR(K69="",G69=""),"",K69-G69) -> 425 | N69: =J69-E69 -> 20
A70: 60 | B70: フード | C70: 温製おつまみ | D70: たこ焼き | E70: 583 | F70: =IF(E70="","",ROUND(E70/(1+$C$4),0)) -> 530 | G70: 193.1 | H70: =IF(OR(F70="",F70=0,G70=""),"",G70/F70) -> 0.36433962 | I70: =IF(OR(F70="",G70=""),"",F70-G70) -> 336.9 | J70: 603 | K70: =IF(J70="","",ROUND(J70/(1+$D$4),0)) -> 548 | L70: =IF(OR(K70="",K70=0,G70=""),"",G70/K70) -> 0.35237226 | M70: =IF(OR(K70="",G70=""),"",K70-G70) -> 354.9 | N70: =J70-E70 -> 20
A71: 61 | B71: フード | C71: 温製おつまみ | D71: ベーコーン | E71: 583 | F71: =IF(E71="","",ROUND(E71/(1+$C$4),0)) -> 530 | G71: 160.3 | H71: =IF(OR(F71="",F71=0,G71=""),"",G71/F71) -> 0.30245283 | I71: =IF(OR(F71="",G71=""),"",F71-G71) -> 369.7 | J71: 603 | K71: =IF(J71="","",ROUND(J71/(1+$D$4),0)) -> 548 | L71: =IF(OR(K71="",K71=0,G71=""),"",G71/K71) -> 0.29251825 | M71: =IF(OR(K71="",G71=""),"",K71-G71) -> 387.7 | N71: =J71-E71 -> 20
A72: 62 | B72: フード | C72: 温製おつまみ | D72: ベーコンとほうれん草のソテー | E72: 583 | F72: =IF(E72="","",ROUND(E72/(1+$C$4),0)) -> 530 | G72: 220.9 | H72: =IF(OR(F72="",F72=0,G72=""),"",G72/F72) -> 0.41679245 | I72: =IF(OR(F72="",G72=""),"",F72-G72) -> 309.1 | J72: 603 | K72: =IF(J72="","",ROUND(J72/(1+$D$4),0)) -> 548 | L72: =IF(OR(K72="",K72=0,G72=""),"",G72/K72) -> 0.40310219 | M72: =IF(OR(K72="",G72=""),"",K72-G72) -> 327.1 | N72: =J72-E72 -> 20 | O72: レシピなし／原価未登録
A73: 63 | B73: フード | C73: 温製おつまみ | D73: おつまみマヨコーンピザ | E73: 858 | F73: =IF(E73="","",ROUND(E73/(1+$C$4),0)) -> 780 | G73: 238.4 | H73: =IF(OR(F73="",F73=0,G73=""),"",G73/F73) -> 0.30564103 | I73: =IF(OR(F73="",G73=""),"",F73-G73) -> 541.6 | J73: 878 | K73: =IF(J73="","",ROUND(J73/(1+$D$4),0)) -> 798 | L73: =IF(OR(K73="",K73=0,G73=""),"",G73/K73) -> 0.29874687 | M73: =IF(OR(K73="",G73=""),"",K73-G73) -> 559.6 | N73: =J73-E73 -> 20
A74: 64 | B74: フード | C74: 温製おつまみ | D74: アヒージョ | E74: 968 | F74: =IF(E74="","",ROUND(E74/(1+$C$4),0)) -> 880 | G74: 390.3 | H74: =IF(OR(F74="",F74=0,G74=""),"",G74/F74) -> 0.44352273 | I74: =IF(OR(F74="",G74=""),"",F74-G74) -> 489.7 | J74: 988 | K74: =IF(J74="","",ROUND(J74/(1+$D$4),0)) -> 898 | L74: =IF(OR(K74="",K74=0,G74=""),"",G74/K74) -> 0.43463252 | M74: =IF(OR(K74="",G74=""),"",K74-G74) -> 507.7 | N74: =J74-E74 -> 20
A75: 65 | B75: フード | C75: 温製おつまみ | D75: 旨カラ牛バラ | E75: 748 | F75: =IF(E75="","",ROUND(E75/(1+$C$4),0)) -> 680 | G75: 304 | H75: =IF(OR(F75="",F75=0,G75=""),"",G75/F75) -> 0.44705882 | I75: =IF(OR(F75="",G75=""),"",F75-G75) -> 376 | J75: 768 | K75: =IF(J75="","",ROUND(J75/(1+$D$4),0)) -> 698 | L75: =IF(OR(K75="",K75=0,G75=""),"",G75/K75) -> 0.43553009 | M75: =IF(OR(K75="",G75=""),"",K75-G75) -> 394 | N75: =J75-E75 -> 20
A76: 66 | B76: フード | C76: 温製おつまみ | D76: ミニじゃがバター | E76: 418 | F76: =IF(E76="","",ROUND(E76/(1+$C$4),0)) -> 380 | G76: 88.1 | H76: =IF(OR(F76="",F76=0,G76=""),"",G76/F76) -> 0.23184211 | I76: =IF(OR(F76="",G76=""),"",F76-G76) -> 291.9 | J76: 438 | K76: =IF(J76="","",ROUND(J76/(1+$D$4),0)) -> 398 | L76: =IF(OR(K76="",K76=0,G76=""),"",G76/K76) -> 0.22135678 | M76: =IF(OR(K76="",G76=""),"",K76-G76) -> 309.9 | N76: =J76-E76 -> 20
A77: 67 | B77: フード | C77: ピザ | D77: マルゲリータ | E77: 1738 | F77: =IF(E77="","",ROUND(E77/(1+$C$4),0)) -> 1580 | G77: 493.6 | H77: =IF(OR(F77="",F77=0,G77=""),"",G77/F77) -> 0.31240506 | I77: =IF(OR(F77="",G77=""),"",F77-G77) -> 1086.4 | J77: 1768 | K77: =IF(J77="","",ROUND(J77/(1+$D$4),0)) -> 1607 | L77: =IF(OR(K77="",K77=0,G77=""),"",G77/K77) -> 0.30715619 | M77: =IF(OR(K77="",G77=""),"",K77-G77) -> 1113.4 | N77: =J77-E77 -> 30 | O77: 原価未入力（元データ0円）
A78: 68 | B78: フード | C78: ピザ | D78: 特製ガーリックピザ | E78: 2178 | F78: =IF(E78="","",ROUND(E78/(1+$C$4),0)) -> 1980 | G78: 645.3 | H78: =IF(OR(F78="",F78=0,G78=""),"",G78/F78) -> 0.32590909 | I78: =IF(OR(F78="",G78=""),"",F78-G78) -> 1334.7 | J78: 2208 | K78: =IF(J78="","",ROUND(J78/(1+$D$4),0)) -> 2007 | L78: =IF(OR(K78="",K78=0,G78=""),"",G78/K78) -> 0.32152466 | M78: =IF(OR(K78="",G78=""),"",K78-G78) -> 1361.7 | N78: =J78-E78 -> 30 | O78: KENKOコラボ（メニュー表表記：ビーフガーリックピザ）
A79: 69 | B79: フード | C79: ピザ | D79: ビスククリームピザ | E79: 2178 | F79: =IF(E79="","",ROUND(E79/(1+$C$4),0)) -> 1980 | G79: 692.1 | H79: =IF(OR(F79="",F79=0,G79=""),"",G79/F79) -> 0.34954545 | I79: =IF(OR(F79="",G79=""),"",F79-G79) -> 1287.9 | J79: 2208 | K79: =IF(J79="","",ROUND(J79/(1+$D$4),0)) -> 2007 | L79: =IF(OR(K79="",K79=0,G79=""),"",G79/K79) -> 0.34484305 | M79: =IF(OR(K79="",G79=""),"",K79-G79) -> 1314.9 | N79: =J79-E79 -> 30 | O79: KENKOコラボ
A80: 70 | B80: フード | C80: トルティーヤ | D80: トルティーヤ 照り焼きチキン | E80: 638 | F80: =IF(E80="","",ROUND(E80/(1+$C$4),0)) -> 580 | G80: 211.4 | H80: =IF(OR(F80="",F80=0,G80=""),"",G80/F80) -> 0.36448276 | I80: =IF(OR(F80="",G80=""),"",F80-G80) -> 368.6 | J80: 658 | K80: =IF(J80="","",ROUND(J80/(1+$D$4),0)) -> 598 | L80: =IF(OR(K80="",K80=0,G80=""),"",G80/K80) -> 0.35351171 | M80: =IF(OR(K80="",G80=""),"",K80-G80) -> 386.6 | N80: =J80-E80 -> 20 | O80: 要確認：レシピ名「唐揚げてりマヨトルティーヤ」
A81: 71 | B81: フード | C81: トルティーヤ | D81: トルティーヤ サーモンアボカド | E81: 638 | F81: =IF(E81="","",ROUND(E81/(1+$C$4),0)) -> 580 | G81: 189.8 | H81: =IF(OR(F81="",F81=0,G81=""),"",G81/F81) -> 0.32724138 | I81: =IF(OR(F81="",G81=""),"",F81-G81) -> 390.2 | J81: 658 | K81: =IF(J81="","",ROUND(J81/(1+$D$4),0)) -> 598 | L81: =IF(OR(K81="",K81=0,G81=""),"",G81/K81) -> 0.3173913 | M81: =IF(OR(K81="",G81=""),"",K81-G81) -> 408.2 | N81: =J81-E81 -> 20
A82: 72 | B82: フード | C82: トルティーヤ | D82: トルティーヤ コリアンエビ | E82: 638 | F82: =IF(E82="","",ROUND(E82/(1+$C$4),0)) -> 580 | G82: 183.8 | H82: =IF(OR(F82="",F82=0,G82=""),"",G82/F82) -> 0.31689655 | I82: =IF(OR(F82="",G82=""),"",F82-G82) -> 396.2 | J82: 658 | K82: =IF(J82="","",ROUND(J82/(1+$D$4),0)) -> 598 | L82: =IF(OR(K82="",K82=0,G82=""),"",G82/K82) -> 0.30735786 | M82: =IF(OR(K82="",G82=""),"",K82-G82) -> 414.2 | N82: =J82-E82 -> 20
A83: 73 | B83: フード | C83: トルティーヤ | D83: トルティーヤ 生ハムカマンベール | E83: 638 | F83: =IF(E83="","",ROUND(E83/(1+$C$4),0)) -> 580 | G83: 186.2 | H83: =IF(OR(F83="",F83=0,G83=""),"",G83/F83) -> 0.32103448 | I83: =IF(OR(F83="",G83=""),"",F83-G83) -> 393.8 | J83: 658 | K83: =IF(J83="","",ROUND(J83/(1+$D$4),0)) -> 598 | L83: =IF(OR(K83="",K83=0,G83=""),"",G83/K83) -> 0.31137124 | M83: =IF(OR(K83="",G83=""),"",K83-G83) -> 411.8 | N83: =J83-E83 -> 20
A84: 74 | B84: フード | C84: トルティーヤ | D84: トルティーヤ エビフライ | E84: 638 | F84: =IF(E84="","",ROUND(E84/(1+$C$4),0)) -> 580 | G84: 230.6 | H84: =IF(OR(F84="",F84=0,G84=""),"",G84/F84) -> 0.39758621 | I84: =IF(OR(F84="",G84=""),"",F84-G84) -> 349.4 | J84: 658 | K84: =IF(J84="","",ROUND(J84/(1+$D$4),0)) -> 598 | L84: =IF(OR(K84="",K84=0,G84=""),"",G84/K84) -> 0.38561873 | M84: =IF(OR(K84="",G84=""),"",K84-G84) -> 367.4 | N84: =J84-E84 -> 20
A85: 75 | B85: フード | C85: ディッシュ | D85: ハンバーグディッシュ（デミソース） | E85: 1738 | F85: =IF(E85="","",ROUND(E85/(1+$C$4),0)) -> 1580 | G85: 514 | H85: =IF(OR(F85="",F85=0,G85=""),"",G85/F85) -> 0.32531646 | I85: =IF(OR(F85="",G85=""),"",F85-G85) -> 1066 | J85: 1788 | K85: =IF(J85="","",ROUND(J85/(1+$D$4),0)) -> 1625 | L85: =IF(OR(K85="",K85=0,G85=""),"",G85/K85) -> 0.31630769 | M85: =IF(OR(K85="",G85=""),"",K85-G85) -> 1111 | N85: =J85-E85 -> 50
A86: 76 | B86: フード | C86: ディッシュ | D86: チキンディッシュ（トマトソース） | E86: 1738 | F86: =IF(E86="","",ROUND(E86/(1+$C$4),0)) -> 1580 | G86: 550 | H86: =IF(OR(F86="",F86=0,G86=""),"",G86/F86) -> 0.34810127 | I86: =IF(OR(F86="",G86=""),"",F86-G86) -> 1030 | J86: 1788 | K86: =IF(J86="","",ROUND(J86/(1+$D$4),0)) -> 1625 | L86: =IF(OR(K86="",K86=0,G86=""),"",G86/K86) -> 0.33846154 | M86: =IF(OR(K86="",G86=""),"",K86-G86) -> 1075 | N86: =J86-E86 -> 50
A87: 77 | B87: フード | C87: ディッシュ | D87: ポークカツディッシュ（デミソース） | E87: 1738 | F87: =IF(E87="","",ROUND(E87/(1+$C$4),0)) -> 1580 | G87: 526.2 | H87: =IF(OR(F87="",F87=0,G87=""),"",G87/F87) -> 0.33303797 | I87: =IF(OR(F87="",G87=""),"",F87-G87) -> 1053.8 | J87: 1788 | K87: =IF(J87="","",ROUND(J87/(1+$D$4),0)) -> 1625 | L87: =IF(OR(K87="",K87=0,G87=""),"",G87/K87) -> 0.32381538 | M87: =IF(OR(K87="",G87=""),"",K87-G87) -> 1098.8 | N87: =J87-E87 -> 50
A88: 78 | B88: フード | C88: カレー | D88: プレミアムロースかつカレー | E88: 1518 | F88: =IF(E88="","",ROUND(E88/(1+$C$4),0)) -> 1380 | G88: 492.4 | H88: =IF(OR(F88="",F88=0,G88=""),"",G88/F88) -> 0.35681159 | I88: =IF(OR(F88="",G88=""),"",F88-G88) -> 887.6 | J88: 1548 | K88: =IF(J88="","",ROUND(J88/(1+$D$4),0)) -> 1407 | L88: =IF(OR(K88="",K88=0,G88=""),"",G88/K88) -> 0.34996446 | M88: =IF(OR(K88="",G88=""),"",K88-G88) -> 914.6 | N88: =J88-E88 -> 30 | O88: 原価計算エラー（元データ）
A89: 79 | B89: フード | C89: カレー | D89: バターチキンカレー | E89: 1188 | F89: =IF(E89="","",ROUND(E89/(1+$C$4),0)) -> 1080 | G89: 360 | H89: =IF(OR(F89="",F89=0,G89=""),"",G89/F89) -> 0.33333333 | I89: =IF(OR(F89="",G89=""),"",F89-G89) -> 720 | J89: 1218 | K89: =IF(J89="","",ROUND(J89/(1+$D$4),0)) -> 1107 | L89: =IF(OR(K89="",K89=0,G89=""),"",G89/K89) -> 0.32520325 | M89: =IF(OR(K89="",G89=""),"",K89-G89) -> 747 | N89: =J89-E89 -> 30
A90: 80 | B90: フード | C90: カレー | D90: 近江牛ミンチカレー | E90: 1628 | F90: =IF(E90="","",ROUND(E90/(1+$C$4),0)) -> 1480 | G90: 483.6 | H90: =IF(OR(F90="",F90=0,G90=""),"",G90/F90) -> 0.32675676 | I90: =IF(OR(F90="",G90=""),"",F90-G90) -> 996.4 | J90: 1658 | K90: =IF(J90="","",ROUND(J90/(1+$D$4),0)) -> 1507 | L90: =IF(OR(K90="",K90=0,G90=""),"",G90/K90) -> 0.32090246 | M90: =IF(OR(K90="",G90=""),"",K90-G90) -> 1023.4 | N90: =J90-E90 -> 30 | O90: 要確認：レシピ名「キーマカレー」
A91: 81 | B91: フード | C91: カレー | D91: today'sカレー | E91: 1078 | F91: =IF(E91="","",ROUND(E91/(1+$C$4),0)) -> 980 | G91: 215.3 | H91: =IF(OR(F91="",F91=0,G91=""),"",G91/F91) -> 0.21969388 | I91: =IF(OR(F91="",G91=""),"",F91-G91) -> 764.7 | J91: 1098 | K91: =IF(J91="","",ROUND(J91/(1+$D$4),0)) -> 998 | L91: =IF(OR(K91="",K91=0,G91=""),"",G91/K91) -> 0.21573146 | M91: =IF(OR(K91="",G91=""),"",K91-G91) -> 782.7 | N91: =J91-E91 -> 20 | O91: リストは1,023／メニュー表PDFは1,078
A92: 82 | B92: フード | C92: カレー | D92: today'sカレー（ランチセット） | E92: 1133 | F92: =IF(E92="","",ROUND(E92/(1+$C$4),0)) -> 1030 | G92: 353.4 | H92: =IF(OR(F92="",F92=0,G92=""),"",G92/F92) -> 0.3431068 | I92: =IF(OR(F92="",G92=""),"",F92-G92) -> 676.6 | J92: 1153 | K92: =IF(J92="","",ROUND(J92/(1+$D$4),0)) -> 1048 | L92: =IF(OR(K92="",K92=0,G92=""),"",G92/K92) -> 0.33721374 | M92: =IF(OR(K92="",G92=""),"",K92-G92) -> 694.6 | N92: =J92-E92 -> 20 | O92: レシピなし／原価未登録
A93: 83 | B93: フード | C93: リゾット・煮込み | D93: カルボナーラリゾット | E93: 1188 | F93: =IF(E93="","",ROUND(E93/(1+$C$4),0)) -> 1080 | G93: 375.6 | H93: =IF(OR(F93="",F93=0,G93=""),"",G93/F93) -> 0.34777778 | I93: =IF(OR(F93="",G93=""),"",F93-G93) -> 704.4 | J93: 1208 | K93: =IF(J93="","",ROUND(J93/(1+$D$4),0)) -> 1098 | L93: =IF(OR(K93="",K93=0,G93=""),"",G93/K93) -> 0.3420765 | M93: =IF(OR(K93="",G93=""),"",K93-G93) -> 722.4 | N93: =J93-E93 -> 20
A94: 84 | B94: フード | C94: リゾット・煮込み | D94: ビスクリゾット | E94: 1188 | F94: =IF(E94="","",ROUND(E94/(1+$C$4),0)) -> 1080 | G94: 392.4 | H94: =IF(OR(F94="",F94=0,G94=""),"",G94/F94) -> 0.36333333 | I94: =IF(OR(F94="",G94=""),"",F94-G94) -> 687.6 | J94: 1208 | K94: =IF(J94="","",ROUND(J94/(1+$D$4),0)) -> 1098 | L94: =IF(OR(K94="",K94=0,G94=""),"",G94/K94) -> 0.35737705 | M94: =IF(OR(K94="",G94=""),"",K94-G94) -> 705.6 | N94: =J94-E94 -> 20
A95: 85 | B95: フード | C95: リゾット・煮込み | D95: カレーリゾット | E95: 1188 | F95: =IF(E95="","",ROUND(E95/(1+$C$4),0)) -> 1080 | G95: 287.4 | H95: =IF(OR(F95="",F95=0,G95=""),"",G95/F95) -> 0.26611111 | I95: =IF(OR(F95="",G95=""),"",F95-G95) -> 792.6 | J95: 1208 | K95: =IF(J95="","",ROUND(J95/(1+$D$4),0)) -> 1098 | L95: =IF(OR(K95="",K95=0,G95=""),"",G95/K95) -> 0.26174863 | M95: =IF(OR(K95="",G95=""),"",K95-G95) -> 810.6 | N95: =J95-E95 -> 20
A96: 86 | B96: フード | C96: リゾット・煮込み | D96: チキンのトマト煮込み | E96: 968 | F96: =IF(E96="","",ROUND(E96/(1+$C$4),0)) -> 880 | G96: 348.6 | H96: =IF(OR(F96="",F96=0,G96=""),"",G96/F96) -> 0.39613636 | I96: =IF(OR(F96="",G96=""),"",F96-G96) -> 531.4 | J96: 988 | K96: =IF(J96="","",ROUND(J96/(1+$D$4),0)) -> 898 | L96: =IF(OR(K96="",K96=0,G96=""),"",G96/K96) -> 0.38819599 | M96: =IF(OR(K96="",G96=""),"",K96-G96) -> 549.4 | N96: =J96-E96 -> 20
A97: 87 | B97: フード | C97: リゾット・煮込み | D97: 煮込みハンバーグ | E97: 968 | F97: =IF(E97="","",ROUND(E97/(1+$C$4),0)) -> 880 | G97: 294 | H97: =IF(OR(F97="",F97=0,G97=""),"",G97/F97) -> 0.33409091 | I97: =IF(OR(F97="",G97=""),"",F97-G97) -> 586 | J97: 988 | K97: =IF(J97="","",ROUND(J97/(1+$D$4),0)) -> 898 | L97: =IF(OR(K97="",K97=0,G97=""),"",G97/K97) -> 0.32739421 | M97: =IF(OR(K97="",G97=""),"",K97-G97) -> 604 | N97: =J97-E97 -> 20
A98: 88 | B98: フード | C98: 肉料理・プレートライス | D98: サーロインステーキ | E98: 2178 | F98: =IF(E98="","",ROUND(E98/(1+$C$4),0)) -> 1980 | G98: 810 | H98: =IF(OR(F98="",F98=0,G98=""),"",G98/F98) -> 0.40909091 | I98: =IF(OR(F98="",G98=""),"",F98-G98) -> 1170 | J98: 2228 | K98: =IF(J98="","",ROUND(J98/(1+$D$4),0)) -> 2025 | L98: =IF(OR(K98="",K98=0,G98=""),"",G98/K98) -> 0.4 | M98: =IF(OR(K98="",G98=""),"",K98-G98) -> 1215 | N98: =J98-E98 -> 50 | O98: レシピなし／原価未登録
A99: 89 | B99: フード | C99: 肉料理・プレートライス | D99: お肉みっちみち！ジャーマンヴルスト | E99: 1078 | F99: =IF(E99="","",ROUND(E99/(1+$C$4),0)) -> 980 | G99: 371.3 | H99: =IF(OR(F99="",F99=0,G99=""),"",G99/F99) -> 0.37887755 | I99: =IF(OR(F99="",G99=""),"",F99-G99) -> 608.7 | J99: 1128 | K99: =IF(J99="","",ROUND(J99/(1+$D$4),0)) -> 1025 | L99: =IF(OR(K99="",K99=0,G99=""),"",G99/K99) -> 0.3622439 | M99: =IF(OR(K99="",G99=""),"",K99-G99) -> 653.7 | N99: =J99-E99 -> 50 | O99: レシピなし／原価未登録
A100: 90 | B100: フード | C100: 肉料理・プレートライス | D100: 仙台牛タンのグリル | E100: 1848 | F100: =IF(E100="","",ROUND(E100/(1+$C$4),0)) -> 1680 | G100: 639.7 | H100: =IF(OR(F100="",F100=0,G100=""),"",G100/F100) -> 0.38077381 | I100: =IF(OR(F100="",G100=""),"",F100-G100) -> 1040.3 | J100: 1898 | K100: =IF(J100="","",ROUND(J100/(1+$D$4),0)) -> 1725 | L100: =IF(OR(K100="",K100=0,G100=""),"",G100/K100) -> 0.37084058 | M100: =IF(OR(K100="",G100=""),"",K100-G100) -> 1085.3 | N100: =J100-E100 -> 50 | O100: レシピなし／原価未登録
...

Sheet 分類別サマリー
A1: 分類別サマリー（一覧シートの原価を変更すると自動更新）
A3: 区分 | B3: 分類 | C3: 品数 | D3: うち原価未登録 | E3: 平均原価率 | F3: 平均粗利益
A4: ドリンク | B4: ビール | C4: =COUNTIF(メニュー原価一覧!$C$11:$C$159,B4) -> 9 | D4: =C4-COUNTIFS(メニュー原価一覧!$C$11:$C$159,B4,メニュー原価一覧!$G$11:$G$159,">0") -> 0 | E4: =IFERROR(AVERAGEIFS(メニュー原価一覧!$H$11:$H$159,メニュー原価一覧!$C$11:$C$159,B4,メニュー原価一覧!$G$11:$G$159,">0"),"-") -> 0.3817268 | F4: =IFERROR(AVERAGEIFS(メニュー原価一覧!$I$11:$I$159,メニュー原価一覧!$C$11:$C$159,B4,メニュー原価一覧!$G$11:$G$159,">0"),"-") -> 492
A5: ドリンク | B5: ハイボール | C5: =COUNTIF(メニュー原価一覧!$C$11:$C$159,B5) -> 5 | D5: =C5-COUNTIFS(メニュー原価一覧!$C$11:$C$159,B5,メニュー原価一覧!$G$11:$G$159,">0") -> 0 | E5: =IFERROR(AVERAGEIFS(メニュー原価一覧!$H$11:$H$159,メニュー原価一覧!$C$11:$C$159,B5,メニュー原価一覧!$G$11:$G$159,">0"),"-") -> 0.21320588 | F5: =IFERROR(AVERAGEIFS(メニュー原価一覧!$I$11:$I$159,メニュー原価一覧!$C$11:$C$159,B5,メニュー原価一覧!$G$11:$G$159,">0"),"-") -> 535.02
A6: ドリンク | B6: サワー | C6: =COUNTIF(メニュー原価一覧!$C$11:$C$159,B6) -> 9 | D6: =C6-COUNTIFS(メニュー原価一覧!$C$11:$C$159,B6,メニュー原価一覧!$G$11:$G$159,">0") -> 0 | E6: =IFERROR(AVERAGEIFS(メニュー原価一覧!$H$11:$H$159,メニュー原価一覧!$C$11:$C$159,B6,メニュー原価一覧!$G$11:$G$159,">0"),"-") -> 0.15328139 | F6: =IFERROR(AVERAGEIFS(メニュー原価一覧!$I$11:$I$159,メニュー原価一覧!$C$11:$C$159,B6,メニュー原価一覧!$G$11:$G$159,">0"),"-") -> 491.09679
A7: ドリンク | B7: カクテル・蒸留酒・焼酎 | C7: =COUNTIF(メニュー原価一覧!$C$11:$C$159,B7) -> 8 | D7: =C7-COUNTIFS(メニュー原価一覧!$C$11:$C$159,B7,メニュー原価一覧!$G$11:$G$159,">0") -> 0 | E7: =IFERROR(AVERAGEIFS(メニュー原価一覧!$H$11:$H$159,メニュー原価一覧!$C$11:$C$159,B7,メニュー原価一覧!$G$11:$G$159,">0"),"-") -> 0.17979726 | F7: =IFERROR(AVERAGEIFS(メニュー原価一覧!$I$11:$I$159,メニュー原価一覧!$C$11:$C$159,B7,メニュー原価一覧!$G$11:$G$159,">0"),"-") -> 475.71759
A8: ドリンク | B8: ワイン・果実酒 | C8: =COUNTIF(メニュー原価一覧!$C$11:$C$159,B8) -> 7 | D8: =C8-COUNTIFS(メニュー原価一覧!$C$11:$C$159,B8,メニュー原価一覧!$G$11:$G$159,">0") -> 0 | E8: =IFERROR(AVERAGEIFS(メニュー原価一覧!$H$11:$H$159,メニュー原価一覧!$C$11:$C$159,B8,メニュー原価一覧!$G$11:$G$159,">0"),"-") -> 0.32386228 | F8: =IFERROR(AVERAGEIFS(メニュー原価一覧!$I$11:$I$159,メニュー原価一覧!$C$11:$C$159,B8,メニュー原価一覧!$G$11:$G$159,">0"),"-") -> 651.78571
A9: ドリンク | B9: セット | C9: =COUNTIF(メニュー原価一覧!$C$11:$C$159,B9) -> 2 | D9: =C9-COUNTIFS(メニュー原価一覧!$C$11:$C$159,B9,メニュー原価一覧!$G$11:$G$159,">0") -> 2 | E9: =IFERROR(AVERAGEIFS(メニュー原価一覧!$H$11:$H$159,メニュー原価一覧!$C$11:$C$159,B9,メニュー原価一覧!$G$11:$G$159,">0"),"-") -> - | F9: =IFERROR(AVERAGEIFS(メニュー原価一覧!$I$11:$I$159,メニュー原価一覧!$C$11:$C$159,B9,メニュー原価一覧!$G$11:$G$159,">0"),"-") -> -
A10: フード | B10: 冷製おつまみ | C10: =COUNTIF(メニュー原価一覧!$C$11:$C$159,B10) -> 13 | D10: =C10-COUNTIFS(メニュー原価一覧!$C$11:$C$159,B10,メニュー原価一覧!$G$11:$G$159,">0") -> 1 | E10: =IFERROR(AVERAGEIFS(メニュー原価一覧!$H$11:$H$159,メニュー原価一覧!$C$11:$C$159,B10,メニュー原価一覧!$G$11:$G$159,">0"),"-") -> 0.36093877 | F10: =IFERROR(AVERAGEIFS(メニュー原価一覧!$I$11:$I$159,メニュー原価一覧!$C$11:$C$159,B10,メニュー原価一覧!$G$11:$G$159,">0"),"-") -> 355.59167
A11: フード | B11: 温製おつまみ | C11: =COUNTIF(メニュー原価一覧!$C$11:$C$159,B11) -> 13 | D11: =C11-COUNTIFS(メニュー原価一覧!$C$11:$C$159,B11,メニュー原価一覧!$G$11:$G$159,">0") -> 0 | E11: =IFERROR(AVERAGEIFS(メニュー原価一覧!$H$11:$H$159,メニュー原価一覧!$C$11:$C$159,B11,メニュー原価一覧!$G$11:$G$159,">0"),"-") -> 0.33360508 | F11: =IFERROR(AVERAGEIFS(メニュー原価一覧!$I$11:$I$159,メニュー原価一覧!$C$11:$C$159,B11,メニュー原価一覧!$G$11:$G$159,">0"),"-") -> 415.90769
A12: フード | B12: ピザ | C12: =COUNTIF(メニュー原価一覧!$C$11:$C$159,B12) -> 3 | D12: =C12-COUNTIFS(メニュー原価一覧!$C$11:$C$159,B12,メニュー原価一覧!$G$11:$G$159,">0") -> 0 | E12: =IFERROR(AVERAGEIFS(メニュー原価一覧!$H$11:$H$159,メニュー原価一覧!$C$11:$C$159,B12,メニュー原価一覧!$G$11:$G$159,">0"),"-") -> 0.32928654 | F12: =IFERROR(AVERAGEIFS(メニュー原価一覧!$I$11:$I$159,メニュー原価一覧!$C$11:$C$159,B12,メニュー原価一覧!$G$11:$G$159,">0"),"-") -> 1236.3333
A13: フード | B13: トルティーヤ | C13: =COUNTIF(メニュー原価一覧!$C$11:$C$159,B13) -> 5 | D13: =C13-COUNTIFS(メニュー原価一覧!$C$11:$C$159,B13,メニュー原価一覧!$G$11:$G$159,">0") -> 0 | E13: =IFERROR(AVERAGEIFS(メニュー原価一覧!$H$11:$H$159,メニュー原価一覧!$C$11:$C$159,B13,メニュー原価一覧!$G$11:$G$159,">0"),"-") -> 0.34544828 | F13: =IFERROR(AVERAGEIFS(メニュー原価一覧!$I$11:$I$159,メニュー原価一覧!$C$11:$C$159,B13,メニュー原価一覧!$G$11:$G$159,">0"),"-") -> 379.64
A14: フード | B14: ディッシュ | C14: =COUNTIF(メニュー原価一覧!$C$11:$C$159,B14) -> 3 | D14: =C14-COUNTIFS(メニュー原価一覧!$C$11:$C$159,B14,メニュー原価一覧!$G$11:$G$159,">0") -> 0 | E14: =IFERROR(AVERAGEIFS(メニュー原価一覧!$H$11:$H$159,メニュー原価一覧!$C$11:$C$159,B14,メニュー原価一覧!$G$11:$G$159,">0"),"-") -> 0.33548523 | F14: =IFERROR(AVERAGEIFS(メニュー原価一覧!$I$11:$I$159,メニュー原価一覧!$C$11:$C$159,B14,メニュー原価一覧!$G$11:$G$159,">0"),"-") -> 1049.9333
A15: フード | B15: カレー | C15: =COUNTIF(メニュー原価一覧!$C$11:$C$159,B15) -> 5 | D15: =C15-COUNTIFS(メニュー原価一覧!$C$11:$C$159,B15,メニュー原価一覧!$G$11:$G$159,">0") -> 0 | E15: =IFERROR(AVERAGEIFS(メニュー原価一覧!$H$11:$H$159,メニュー原価一覧!$C$11:$C$159,B15,メニュー原価一覧!$G$11:$G$159,">0"),"-") -> 0.31594047 | F15: =IFERROR(AVERAGEIFS(メニュー原価一覧!$I$11:$I$159,メニュー原価一覧!$C$11:$C$159,B15,メニュー原価一覧!$G$11:$G$159,">0"),"-") -> 809.06
... A25: フード | B25: デザート | C25: =COUNTIF(メニュー原価一覧!$C$11:$C$159,B25) -> 12 | D25: =C25-COUNTIFS(メニュー原価一覧!$C$11:$C$159,B25,メニュー原価一覧!$G$11:$G$159,">0") -> 0 | E25: =IFERROR(AVERAGEIFS(メニュー原価一覧!$H$11:$H$159,メニュー原価一覧!$C$11:$C$159,B25,メニュー原価一覧!$G$11:$G$159,">0"),"-") -> 0.21571632 | F25: =IFERROR(AVERAGEIFS(メニュー原価一覧!$I$11:$I$159,メニュー原価一覧!$C$11:$C$159,B25,メニュー原価一覧!$G$11:$G$159,">0"),"-") -> 392.68333
A26: 合計 | C26: =SUM(C4:C25) -> 149 | D26: =SUM(D4:D25) -> 3 | E26: =メニュー原価一覧!C6 -> 0.28549818 | F26: =メニュー原価一覧!C7 -> 516.42248
